MANIFEST.in
setup.py
appinit/__init__.py
appinit/__main__.py
appinit/command.py
appinit/environ.py
appinit/utils.py
appinit.egg-info/PKG-INFO
appinit.egg-info/SOURCES.txt
appinit.egg-info/dependency_links.txt
appinit.egg-info/entry_points.txt
appinit.egg-info/top_level.txt
appinit/_vendor/__init__.py
appinit/_vendor/pkg_resources/__init__.py
appinit/_vendor/pkg_resources/_vendor/__init__.py
appinit/_vendor/pkg_resources/_vendor/packaging/__about__.py
appinit/_vendor/pkg_resources/_vendor/packaging/__init__.py
appinit/_vendor/pkg_resources/_vendor/packaging/_compat.py
appinit/_vendor/pkg_resources/_vendor/packaging/_structures.py
appinit/_vendor/pkg_resources/_vendor/packaging/specifiers.py
appinit/_vendor/pkg_resources/_vendor/packaging/version.py
appinit/apps/__init__.py
appinit/apps/core.py
appinit/apps/houdini/__init__.py
appinit/apps/houdini/app.py
appinit/apps/houdini/runtime.py
appinit/apps/houdini/sandbox/python2.7libs/pythonrc.py
appinit/apps/houdini/sandbox/scripts/123.py
appinit/apps/houdini/sandbox/scripts/456.py
appinit/apps/it/__init__.py
appinit/apps/it/app.py
appinit/apps/it/sandbox/appinit.py
appinit/apps/mari/__init__.py
appinit/apps/mari/app.py
appinit/apps/mari/runtime.py
appinit/apps/mari/sandbox/init.py
appinit/apps/mari/sandbox/menu.py
appinit/apps/maya/__init__.py
appinit/apps/maya/app.py
appinit/apps/maya/runtime.py
appinit/apps/maya/sandbox/userSetup.py
appinit/apps/nuke/__init__.py
appinit/apps/nuke/app.py
appinit/apps/nuke/runtime.py
appinit/apps/nuke/sandbox/init.py
appinit/apps/nuke/sandbox/menu.py