Metadata-Version: 1.0
Name: appinit
Version: 1.0.0
Summary: Unified startup for VFX applications.
Home-page: http://github.com/vfxetc/appinit
Author: Mike Boers
Author-email: floss+appinit@vfxetc.com
License: BSD-3
Platform: UNKNOWN
